argumentation/__init__.py
argumentation/py.typed
argumentation-0.1.0.dist-info/METADATA
argumentation-0.1.0.dist-info/WHEEL
argumentation-0.1.0.dist-info/licenses/LICENSE
argumentation-0.1.0.dist-info/RECORD
