Metadata-Version: 2.4
Name: argumentation
Version: 0.1.0
Summary: Python argument parser for complex applications
Project-URL: Homepage, https://github.com/nyxkrage/argumentation
Project-URL: Issues, https://github.com/nyxkrage/argumentation/issues
Author-email: Carsten Kragelund <carsten@kragelund.dev>
License-Expression: MIT
License-File: LICENSE
Requires-Python: >=3.9
Requires-Dist: pydantic>=2.10.6
Requires-Dist: pyyaml>=6.0.2
Requires-Dist: tomli>=2.2.1; python_full_version < '3.11'
